{
  "id": "475",
  "caseNo": null,
  "incident": "20200612旺角",
  "defendants": [
    {
      "id": "619",
      "name": "*",
      "age": 15,
      "charges": [
        {
          "id": "882",
          "verdict": "成立",
          "plea": "認罪",
          "charge": "公眾妨擾，違反普通法"
        }
      ]
    },
    {
      "id": "620",
      "name": "黃",
      "age": 39,
      "charges": [
        {
          "id": "883",
          "verdict": "成立",
          "plea": "認罪",
          "charge": "參與非法集結，違反 《公安條例》(第245章)  第18條"
        }
      ]
    },
    {
      "id": "618",
      "name": "余",
      "age": 33,
      "charges": [
        {
          "id": "881",
          "verdict": "成立",
          "plea": "認罪",
          "charge": "公眾妨擾，違反普通法"
        }
      ]
    }
  ],
  "description": null,
  "tags": [
    "非法集結",
    "公眾妨擾罪",
    "阻街"
  ],
  "trialDateFrom": null,
  "trialDateTo": null,
  "trialLength": null,
  "verdictDate": null,
  "sentenceDate": "2021-04-20",
  "magistrate": "D1, D3:徐綺薇 D2:陳慧敏",
  "prosecutionRep": null,
  "defendantRep": null,
  "summary": "被控於2020年6月12日在旺角砵蘭街與山東街交界外與其他不知名人士一起參與非法集結。\n\n2020年6月12日為反送中抗爭首次大型衝突「6.12」一周年。警方阻撓市民在添馬公園舉行集會，當日晚上有市民在旺角街頭合唱《願榮光歸香港》，卻遭警方驅散。案件於2020年12月7日首度提堂，３名被告原面對一項非法集結罪，王詩麗裁判官批准D1及D2保釋候訊。D3於3月12日認罪，4月1日連同另一宗案件判監７個月。D2在3月30日在陳慧敏裁判官面前承認較輕的妨擾罪，還押至4月20日判刑。",
  "verdict": null,
  "verdictReason": null,
  "sentence": "D1: 監禁４星期，緩刑２年；D2: 160小時社會服務令；D3: ７個月即時監禁（與另案合計總刑期）",
  "sentenceReason": "D1：\n徐官判刑時指，被告在答辯後曾表示會接受服務令，惟受疫情影響，目前輪候履行服務令的人數眾多，被告未必能即時履行服務令以盡快赴外地進行研究。徐官又指，案發時被告曾舉手阻礙的士前進，擾攘了10分鐘，但他沒有叫口號或向司機作出威嚇及挑釁行為，亦沒證據顯示當日交通因而受嚴重阻塞，事件也沒演變為衝突。考慮到本案案情、被告坦白認罪、背景良好等，接納辯方建議，判被告入獄4星期、緩刑2年。\n\nD2：\n陳慧敏裁判官強調法庭須保護公眾，判刑必須對被告人具阻嚇作用。裁判官批評D2行為明顯阻礙車輛前進，並造成漣漪效應，激發更多人加入。\n\n裁判官指社會服務令及感化令報告正面，雖然勞教中心及更生中心報告指D2適合進入兩院所，但考慮本案整體情況，判處160小時社會服務令。\n\nD3：\n被告熱心幫助弱勢社群，受失業影響而犯案，現時已反省，認為應和平理性處理。\n\n案發當晚有人堵路及叫口號，被告參與阻擋的士的行為，威脅公眾安全。而且，被告在一宗2019年10月31日在旺角的刑事損壞案件的法庭保釋期間犯案。\n\n參考過上訴庭案例，法庭必須判處阻嚇性刑罰。本案案情相比之下未如另一宗在2019年8月28日在深水埗的非法集結案件嚴重，故以５個月監禁為量刑起點，但因在法庭擔保期間犯案，加刑１個月認罪扣減1/3，判監４個月。被告另一宗在2019年8月28日在深水埗的非法集結案件在法庭席前處理，而且早前有另一宗2019年10月31日在旺角的刑事損壞案件在另一位裁判官席前判刑，考慮到判刑整體性原則，法庭認為３宗案件在相約時間發生，如果一併在法庭席前處理，會有所調整，故需要整體考慮３宗案件，最終判處總刑期為７個月即時監禁。",
  "bailment": "批准",
  "bailmentRemarks": null,
  "bailmentCondition": null,
  "remarks": null,
  "internalRemarks": null,
  "charges": [
    ""
  ],
  "custodyLength": null,
  "appeal": null,
  "appealJudgementUrl": null,
  "bailmentAppeal": null,
  "complaints": null,
  "publicPerception": null,
  "mediaUrls": [],
  "assigneeId": null,
  "editStatus": "reviewed",
  "references": {
    "nodes": []
  }
}